robot_basic/__init__.py
robot_basic/clipboard.py
robot_basic/date_ope.py
robot_basic/dict.py
robot_basic/file.py
robot_basic/html.py
robot_basic/index.py
robot_basic/json_operate.py
robot_basic/list_ope.py
robot_basic/sql.py
robot_basic/text_ope.py
robot_basic/md_2_html/__init__.py
robot_basic/md_2_html/markdown_2_html.py
robot_basic/md_2_html/highlight/__init__.py
robot_basic/md_2_html/highlight/css_transform.py
robot_basic/md_2_html/highlight/highlight.pack.js
robot_basic/md_2_html/highlight/renderer_code.js
robot_basic/md_2_html/highlight/renderer_code.py
robot_basic/md_2_html/highlight/styles/a11y-dark.min.css
robot_basic/md_2_html/highlight/styles/a11y-light.min.css
robot_basic/md_2_html/highlight/styles/agate.min.css
robot_basic/md_2_html/highlight/styles/an-old-hope.min.css
robot_basic/md_2_html/highlight/styles/androidstudio.min.css
robot_basic/md_2_html/highlight/styles/arduino-light.min.css
robot_basic/md_2_html/highlight/styles/arta.min.css
robot_basic/md_2_html/highlight/styles/ascetic.min.css
robot_basic/md_2_html/highlight/styles/atom-one-dark-reasonable.min.css
robot_basic/md_2_html/highlight/styles/atom-one-dark.min.css
robot_basic/md_2_html/highlight/styles/atom-one-light.min.css
robot_basic/md_2_html/highlight/styles/brown-paper.min.css
robot_basic/md_2_html/highlight/styles/brown-papersq.png
robot_basic/md_2_html/highlight/styles/codepen-embed.min.css
robot_basic/md_2_html/highlight/styles/color-brewer.min.css
robot_basic/md_2_html/highlight/styles/dark.min.css
robot_basic/md_2_html/highlight/styles/default.min.css
robot_basic/md_2_html/highlight/styles/devibeans.min.css
robot_basic/md_2_html/highlight/styles/docco.min.css
robot_basic/md_2_html/highlight/styles/far.min.css
robot_basic/md_2_html/highlight/styles/felipec.min.css
robot_basic/md_2_html/highlight/styles/foundation.min.css
robot_basic/md_2_html/highlight/styles/github-dark-dimmed.min.css
robot_basic/md_2_html/highlight/styles/github-dark.min.css
robot_basic-0.3.7.dist-info/METADATA
robot_basic-0.3.7.dist-info/WHEEL
robot_basic-0.3.7.dist-info/RECORD
