Metadata-Version: 2.4
Name: robot_basic
Version: 0.3.7
Summary: robot basic tools
Author: mance
Classifier: License :: OSI Approved :: MIT License
Classifier: Operating System :: OS Independent
Classifier: Programming Language :: Python :: 3
Requires-Python: >=3.11
Requires-Dist: beautifulsoup4
Requires-Dist: cryptography>=45.0.4
Requires-Dist: jinja2
Requires-Dist: lxml
Requires-Dist: markdownify
Requires-Dist: markupsafe==2.0.1
Requires-Dist: mistune
Requires-Dist: numpy
Requires-Dist: pandas
Requires-Dist: pymysql>=1.1.1
Requires-Dist: pyperclip
Requires-Dist: python-dateutil
Requires-Dist: requests
Requires-Dist: sqlalchemy
